{"id": 114461, "acmi_id": "B2003847", "title": "[John Anderson Home Movies: Reel 22]", "title_annotation": "", "slug": "john-anderson-home-movies-reel-22", "creator_credit": "Jack Anderson", "credit_line": "", "headline_credit": "Australia, c. 1950s", "video_links": [], "record_type": "work", "type": "Film", "is_on_display": false, "last_on_display_place": null, "last_on_display_date": null, "is_context_indigenous": false, "material_description": "", "unpublished": false, "external": false, "first_production_date": null, "commissioned": false, "public_domain": false, "external_references": [], "brief_description": "<p>John Robert (Jack) Anderson (1924–1993) was a film distributor, cinema owner and photographer as well as an enthusiastic filmmaker in and around Ballarat in Victoria. Jack developed an interest in film very early at cinema shows and gained his first film experience while serving in WWII, photographing wartime conditions and aircraft involved in the defence of Australia’s north, including the aftermath of the Darwin bombing raid.</p>\n<p>It was whilst working in photographic studios that Jack met his future wife, business partner and fellow film enthusiast Marie Bourke. Starting out by hiring films and showing them around regional Victoria, Jack and Marie established cinemas such as the Astor Cinema in Ararat, Bell Post Hill Drive-In in Geelong and the Southern and Northern Drive-Ins and Vegas 70 Cinema in Ballarat.  In the 1970s, the Anderson family acquired and restored the Regent Theatre in Ballarat which would then become the first multiplex in regional Victoria.</p>\n<p>Along the way, Jack filmed his family and friends activities and outings, horse racing, Ballarat street scenes, motorcycle scrambling and travel scenes on the road – an unusual and wonderful look at life in regional Victoria during the 1940s to the 1960s.</p>\n<p>This film presents holiday footage shot along the Victorian coastline (Portarlington) along with mixed scenes of suburban family life in the 1950s.</p>\n<p>This film was originally made using 16mm film.</p>\n<p>Selected highlights list:<br />\n00:08:06:00 Portarlington Post Office sign<br />\n00:08:15:00 panning shot of Portarlington Pier<br />\n00:08:45:00 woman in 1950s casual wear eating an ice cream in front of a caravan on the beach as she walks toward the camera<br />\n00:08:59:00 nice shot on the beach including umbrellas, boat, man lying down and 40s fashion<br />\n00:17:31:00 footage of a merry-go-round<br />\n00:18:10:00 Christmas tree, children, parents<br />\n00:21:28:00 pan across a bay and town with caravan and car in foreground<br />\n00:22:08:00 caravan and car in foreground as ship leaves port in the background<br />\n00:23:16:00 surfers<br />\n00:35:33:00 young girl with miniature Hill&#8217;s Hoist toy</p>", "constellations_primary": [], "constellations_other": [], "recommendations": [], "creator_credit_for_label": "<p>Jack Anderson</p>", "headline_credit_for_label": "<p>Australia, c. 1950s</p>", "title_for_label": "<p>[John Anderson Home Movies: Reel 22]</p>", "description": "<p>John Robert (Jack) Anderson (1924–1993) was a film distributor, cinema owner and photographer as well as an enthusiastic filmmaker in and around Ballarat in Victoria. Jack developed an interest in film very early at cinema shows and gained his first film experience while serving in WWII, photographing wartime conditions and aircraft involved in the defence of Australia’s north, including the aftermath of the Darwin bombing raid.</p>\n<p>It was whilst working in photographic studios that Jack met his future wife, business partner and fellow film enthusiast Marie Bourke. Starting out by hiring films and showing them around regional Victoria, Jack and Marie established cinemas such as the Astor Cinema in Ararat, Bell Post Hill Drive-In in Geelong and the Southern and Northern Drive-Ins and Vegas 70 Cinema in Ballarat.  In the 1970s, the Anderson family acquired and restored the Regent Theatre in Ballarat which would then become the first multiplex in regional Victoria.</p>\n<p>Along the way, Jack filmed his family and friends activities and outings, horse racing, Ballarat street scenes, motorcycle scrambling and travel scenes on the road – an unusual and wonderful look at life in regional Victoria during the 1940s to the 1960s.</p>\n<p>This film presents holiday footage shot along the Victorian coastline (Portarlington) along with mixed scenes of suburban family life in the 1950s.</p>\n<p>This film was originally made using 16mm film.</p>\n<p>Selected highlights list:<br />\n00:08:06:00 Portarlington Post Office sign<br />\n00:08:15:00 panning shot of Portarlington Pier<br />\n00:08:45:00 woman in 1950s casual wear eating an ice cream in front of a caravan on the beach as she walks toward the camera<br />\n00:08:59:00 nice shot on the beach including umbrellas, boat, man lying down and 40s fashion<br />\n00:17:31:00 footage of a merry-go-round<br />\n00:18:10:00 Christmas tree, children, parents<br />\n00:21:28:00 pan across a bay and town with caravan and car in foreground<br />\n00:22:08:00 caravan and car in foreground as ship leaves port in the background<br />\n00:23:16:00 surfers<br />\n00:35:33:00 young girl with miniature Hill&#8217;s Hoist toy</p>", "description_for_label": ["<p>John Robert (Jack) Anderson (1924–1993) was a film distributor, cinema owner and photographer as well as an enthusiastic filmmaker in and around Ballarat in Victoria. Jack developed an interest in film very early at cinema shows and gained his first film experience while serving in WWII, photographing wartime conditions and aircraft involved in the defence of Australia’s north, including the aftermath of the Darwin bombing raid.</p>\n<p>It was whilst working in photographic studios that Jack met his future wife, business partner and fellow film enthusiast Marie Bourke. Starting out by hiring films and showing them around regional Victoria, Jack and Marie established cinemas such as the Astor Cinema in Ararat, Bell Post Hill Drive-In in Geelong and the Southern and Northern Drive-Ins and Vegas 70 Cinema in Ballarat.  In the 1970s, the Anderson family acquired and restored the Regent Theatre in Ballarat which would then become the first multiplex in regional Victoria.</p>\n<p>Along the way, Jack filmed his family and friends activities and outings, horse racing, Ballarat street scenes, motorcycle scrambling and travel scenes on the road – an unusual and wonderful look at life in regional Victoria during the 1940s to the 1960s.</p>\n<p>This film presents holiday footage shot along the Victorian coastline (Portarlington) along with mixed scenes of suburban family life in the 1950s.</p>\n<p>This film was originally made using 16mm film.</p>\n<p>Selected highlights list:<br />\n00:08:06:00 Portarlington Post Office sign<br />\n00:08:15:00 panning shot of Portarlington Pier<br />\n00:08:45:00 woman in 1950s casual wear eating an ice cream in front of a caravan on the beach as she walks toward the camera<br />\n00:08:59:00 nice shot on the beach including umbrellas, boat, man lying down and 40s fashion<br />\n00:17:31:00 footage of a merry-go-round<br />\n00:18:10:00 Christmas tree, children, parents<br />\n00:21:28:00 pan across a bay and town with caravan and car in foreground<br />\n00:22:08:00 caravan and car in foreground as ship leaves port in the background<br />\n00:23:16:00 surfers<br />\n00:35:33:00 young girl with miniature Hill&#8217;s Hoist toy</p>"], "credit_line_for_label": "", "details": [{"label": "Duration", "display_values": ["00:41:52:00"]}, {"label": "Language", "display_values": ["No spoken word"]}, {"label": "Subject categories", "display_values": ["Amateur & Student Films&nbsp;→ Amateur films", "Anthropology, Ethnology, Exploration & Travel&nbsp;→ Beaches", "Anthropology, Ethnology, Exploration & Travel&nbsp;→ Christmas", "Climate, Environment, Natural Resources & Disasters&nbsp;→ Beaches", "Economics, Philosophy, Politics, Religion & Sociology&nbsp;→ Christmas", "Hobbies, Recreation & Sport&nbsp;→ Beaches", "Hobbies, Recreation & Sport&nbsp;→ Caravans", "Hobbies, Recreation & Sport&nbsp;→ Surfers", "Hobbies, Recreation & Sport&nbsp;→ Surfing", "Hobbies, Recreation & Sport&nbsp;→ Surfing - Australia", "Hobbies, Recreation & Sport&nbsp;→ Toys", "Short films", "Short films&nbsp;→ Short films - Australia"]}, {"label": "Sound/audio", "display_values": ["Silent"]}, {"label": "Colour", "display_values": ["Colour"]}], "stats": {"tap_count": 0}, "links": [], "creators_primary": [{"id": 3112119, "name": "Jack Anderson", "creator_id": 43384, "creator_wikidata_id": null, "role": "creator", "role_id": 968, "is_primary": true}], "creators_other": [], "media_note": null, "holdings": [{"name": "MOV file ProRes4444; Digital Preservation Master - overscan", "identifier": "", "description": ""}, {"name": "MOV file ProRes4444; Digital Preservation Master - presentation", "identifier": "", "description": ""}, {"name": "MPEG-4 Digital File; ACMI Digital Access Copy - overscan", "identifier": "", "description": ""}, {"name": "MPEG-4 Digital File; ACMI Digital Access Copy - presentation", "identifier": "", "description": ""}, {"name": "16mm film; Master", "identifier": "", "description": ""}], "part_of": null, "parts": [], "part_siblings": [], "group": null, "group_works": [], "group_siblings": [], "source": {"name": "Vernon", "slug": "vernon"}, "source_identifier": "176472", "eaas_environment_id": null, "production_places": [{"id": 3, "name": "Australia", "slug": "australia"}], "production_dates": [{"date": "c. 1950s", "notes": "", "to_year": "c. 1950s"}], "labels": [53953]}