{"count": 41723, "next": "https://api.acmi.net.au/works/?page=2354", "previous": "https://api.acmi.net.au/works/?page=2352", "results": [{"id": 92869, "acmi_id": "316209", "title": "The Garden of the Finzi-Continis = Il Giardino dei Finzi-Contini", "title_annotation": "", "slug": "the-garden-of-the-finzi-continis-il-giardino-dei-finzi-contini", "creator_credit": "Vittorio De Sica, Arthur Cohn, Gianni Hecht Lucari, CCC Filmkunst and Documento Films", "credit_line": "", "headline_credit": "Italy, 1970", "video_links": [], "record_type": "work", "type": "Film", "is_on_display": false, "last_on_display_place": null, "last_on_display_date": null, "is_context_indigenous": false, "material_description": "", "unpublished": false, "external": false, "first_production_date": "1970-01-01T10:00:00+10:00", "commissioned": false, "public_domain": false, "external_references": [{"id": 45978, "source": {"name": "Wikidata", "slug": "wikidata"}, "source_identifier": "Q683014"}], "brief_description": "<p>Made towards the end of his life, de Sica&#8217;s &#8220;The Garden of the Finzi-Continis&#8221; is one of the Italian director&#8217;s finest achievements. In this movie de Sica turns his gaze away from the urban working class lives that dominated his neo-realist cinema, and instead focuses on the lives of an aristocratic Jewish family leading up to the tragedy of World War II. Based on Giorgio Bassini&#8217;s acclaimed novel of the same name, the film details the experiences of love, family and politics as seen through the eyes of the adults and the adolescents in the Finzi-Contini family. The children attempt to make their mansion a refuge against fascism, a perpetual romantic space to re-live their childhood games and preoccupations. The adults, in turn, hope that by accommodating to the increasingly humiliating &#8220;race-laws&#8221; they will buy time and live to see the restoration of the old social order. But as Italy joins Germany in war, all their attempts prove futile against the savage anti-Semitism of fascism. In the film&#8217;s devastating concluding passage, the tragedy of European twentieth-century history is conveyed in the stark faces of the family, stripped of their luxuries and belongings; stripped of their illusions and their hope. The film is a loving remembrance of a specifically Italian Jewish history and culture: de Sica&#8217;s ability to immerse us in the textures and colours of a vanquished past is one of this film&#8217;s greatest achievements. It&#8217;s dignified simplicity in presenting the horror of the Holocaust makes it one of the most eloquent of anti-war films. (Awards: Winner of the Academy Award for Best Foreign Language Film. Winner of the Golden Bear at the Venice Film Festival. With Dominique Sanda, Helmut Berger) In Italian with English subtitles.</p>", "constellations_primary": [], "constellations_other": [], "recommendations": [], "creator_credit_for_label": "<p>Vittorio De Sica, Arthur Cohn, Gianni Hecht Lucari, CCC Filmkunst and Documento Films</p>", "headline_credit_for_label": "<p>Italy, 1970</p>", "title_for_label": "<p>The Garden of the Finzi-Continis = Il Giardino dei Finzi-Contini</p>", "description": "<p>Made towards the end of his life, de Sica&#8217;s &#8220;The Garden of the Finzi-Continis&#8221; is one of the Italian director&#8217;s finest achievements. In this movie de Sica turns his gaze away from the urban working class lives that dominated his neo-realist cinema, and instead focuses on the lives of an aristocratic Jewish family leading up to the tragedy of World War II. Based on Giorgio Bassini&#8217;s acclaimed novel of the same name, the film details the experiences of love, family and politics as seen through the eyes of the adults and the adolescents in the Finzi-Contini family. The children attempt to make their mansion a refuge against fascism, a perpetual romantic space to re-live their childhood games and preoccupations. The adults, in turn, hope that by accommodating to the increasingly humiliating &#8220;race-laws&#8221; they will buy time and live to see the restoration of the old social order. But as Italy joins Germany in war, all their attempts prove futile against the savage anti-Semitism of fascism. In the film&#8217;s devastating concluding passage, the tragedy of European twentieth-century history is conveyed in the stark faces of the family, stripped of their luxuries and belongings; stripped of their illusions and their hope. The film is a loving remembrance of a specifically Italian Jewish history and culture: de Sica&#8217;s ability to immerse us in the textures and colours of a vanquished past is one of this film&#8217;s greatest achievements. It&#8217;s dignified simplicity in presenting the horror of the Holocaust makes it one of the most eloquent of anti-war films. (Awards: Winner of the Academy Award for Best Foreign Language Film. Winner of the Golden Bear at the Venice Film Festival. With Dominique Sanda, Helmut Berger) In Italian with English subtitles.</p>", "description_for_label": ["<p>Made towards the end of his life, de Sica&#8217;s &#8220;The Garden of the Finzi-Continis&#8221; is one of the Italian director&#8217;s finest achievements. In this movie de Sica turns his gaze away from the urban working class lives that dominated his neo-realist cinema, and instead focuses on the lives of an aristocratic Jewish family leading up to the tragedy of World War II. Based on Giorgio Bassini&#8217;s acclaimed novel of the same name, the film details the experiences of love, family and politics as seen through the eyes of the adults and the adolescents in the Finzi-Contini family. The children attempt to make their mansion a refuge against fascism, a perpetual romantic space to re-live their childhood games and preoccupations. The adults, in turn, hope that by accommodating to the increasingly humiliating &#8220;race-laws&#8221; they will buy time and live to see the restoration of the old social order. But as Italy joins Germany in war, all their attempts prove futile against the savage anti-Semitism of fascism. In the film&#8217;s devastating concluding passage, the tragedy of European twentieth-century history is conveyed in the stark faces of the family, stripped of their luxuries and belongings; stripped of their illusions and their hope. The film is a loving remembrance of a specifically Italian Jewish history and culture: de Sica&#8217;s ability to immerse us in the textures and colours of a vanquished past is one of this film&#8217;s greatest achievements. It&#8217;s dignified simplicity in presenting the horror of the Holocaust makes it one of the most eloquent of anti-war films. (Awards: Winner of the Academy Award for Best Foreign Language Film. Winner of the Golden Bear at the Venice Film Festival. With Dominique Sanda, Helmut Berger) In Italian with English subtitles.</p>"], "credit_line_for_label": "", "details": [{"label": "Duration", "display_values": ["01:34:00:00"]}, {"label": "Languages", "display_values": ["English", "Italian", "Italian"]}, {"label": "Audience classification", "display_values": ["MA"]}, {"label": "Subject categories", "display_values": ["Adaptations", "Advertising, Film, Journalism, Mass Media & TV&nbsp;→ Academy awards (Motion pictures)", "Advertising, Film, Journalism, Mass Media & TV&nbsp;→ Film festivals - Germany - Berlin - Awards", "Advertising, Film, Journalism, Mass Media & TV&nbsp;→ Foreign language films", "Anthropology, Ethnology, Exploration & Travel&nbsp;→ Family - Italy", "Anthropology, Ethnology, Exploration & Travel&nbsp;→ Italy - Religion", "Armed Forces, Military, War & Weapons&nbsp;→ Holocaust, Jewish (1939-1945", "Armed Forces, Military, War & Weapons&nbsp;→ World War, 1939-1945 - Italy", "Armed Forces, Military, War & Weapons&nbsp;→ World War, 1939-1945 - Jews", "Economics, Philosophy, Politics, Religion & Sociology&nbsp;→ Adolescence", "Economics, Philosophy, Politics, Religion & Sociology&nbsp;→ Fascism", "Economics, Philosophy, Politics, Religion & Sociology&nbsp;→ Italy - Economic conditions", "Economics, Philosophy, Politics, Religion & Sociology&nbsp;→ Italy - Religion", "Family, Gender Identity, Relationships & Sexuality&nbsp;→ Adolescence", "Family, Gender Identity, Relationships & Sexuality&nbsp;→ Family - Italy", "Feature films", "Feature films&nbsp;→ Feature films - Italy", "Food, Health, Lifestyle, Medicine, Psychology & Safety&nbsp;→ Love", "Foreign language films", "History&nbsp;→ Europe - Civilization - 20th century", "History&nbsp;→ Holocaust, Jewish (1939-1945", "History&nbsp;→ Italy - History", "Literature&nbsp;→ Italian literature - Film and video adaptations"]}, {"label": "Sound/audio", "display_values": ["Sound"]}, {"label": "Colour", "display_values": ["Colour"]}], "stats": {"tap_count": 0}, "links": [], "creators_primary": [{"id": 2349893, "name": "Vittorio De Sica", "creator_id": 25893, "creator_wikidata_id": "Q53004", "role": "director", "role_id": 938, "is_primary": true}, {"id": 2349892, "name": "Arthur Cohn", "creator_id": 19763, "creator_wikidata_id": "Q124474", "role": "co-producer", "role_id": 915, "is_primary": true}, {"id": 2349888, "name": "Gianni Hecht Lucari", "creator_id": 80028, "creator_wikidata_id": "Q5558194", "role": "co-producer", "role_id": 915, "is_primary": true}, {"id": 2349883, "name": "CCC Filmkunst", "creator_id": 25131, "creator_wikidata_id": null, "role": "production company", "role_id": 941, "is_primary": true}, {"id": 2349886, "name": "Documento Films", "creator_id": 34574, "creator_wikidata_id": "Q121091057", "role": "production company", "role_id": 941, "is_primary": true}], "creators_other": [], "media_note": "Sorry, we aren't able to make images or video for this item available to the public online.", "holdings": [{"name": "DVD; Access Print (Section 1)", "identifier": "", "description": ""}], "part_of": null, "parts": [], "part_siblings": [], "group": null, "group_works": [], "group_siblings": [], "source": {"name": "Vernon", "slug": "vernon"}, "source_identifier": "50383", "eaas_environment_id": null, "production_places": [{"id": 19, "name": "Italy", "slug": "italy"}], "production_dates": [{"date": "1970", "notes": "Produced", "to_year": "1970"}], "labels": [32359]}, {"id": 92863, "acmi_id": "316203", "title": "Head over heels", "title_annotation": "", "slug": "head-over-heels", "creator_credit": "Mark Waters, Robert Simonds and Universal Studios", "credit_line": "", "headline_credit": "United Kingdom, 2001", "video_links": [], "record_type": "work", "type": "Film", "is_on_display": false, "last_on_display_place": null, "last_on_display_date": null, "is_context_indigenous": false, "material_description": "", "unpublished": false, "external": false, "first_production_date": "2001-01-01T11:00:00+11:00", "commissioned": false, "public_domain": false, "external_references": [{"id": 47666, "source": {"name": "Wikidata", "slug": "wikidata"}, "source_identifier": "Q1542340"}], "brief_description": "<p>Australian supermodel Sarah O&#8217;Hare makes her acting debut as one of four models to share a plush Manhatten apartment with our protagonist, Amanda (Monica Potter). Single Amanda is cursed with dating the wrong men and when she spots handsome Jim Winston (Freddie Prinze Jr,) out her window - a man she met under curious circumstances in the lobby - she becomes instantly attracted and decidedly cautious. Under the guidance of her new flatmates, Amanda crashes a party at Jim&#8217;s and discovers he is almost too good to be true. Voyeurism wreaks havoc between the two soulmates when Amanda sees what she believes to be Jim committing a murder. When the police fail to locate a body she takes it upon herself to get to the bottom of the matter, ably assisted and hindered by her model friends. Cast also includes Ivana Milicevic, Shalom Harlow, Tomiko Fraser and China Chow.</p>", "constellations_primary": [], "constellations_other": [], "recommendations": [], "creator_credit_for_label": "<p>Mark Waters, Robert Simonds and Universal Studios</p>", "headline_credit_for_label": "<p>United Kingdom, 2001</p>", "title_for_label": "<p>Head over heels</p>", "description": "<p>Australian supermodel Sarah O&#8217;Hare makes her acting debut as one of four models to share a plush Manhatten apartment with our protagonist, Amanda (Monica Potter). Single Amanda is cursed with dating the wrong men and when she spots handsome Jim Winston (Freddie Prinze Jr,) out her window - a man she met under curious circumstances in the lobby - she becomes instantly attracted and decidedly cautious. Under the guidance of her new flatmates, Amanda crashes a party at Jim&#8217;s and discovers he is almost too good to be true. Voyeurism wreaks havoc between the two soulmates when Amanda sees what she believes to be Jim committing a murder. When the police fail to locate a body she takes it upon herself to get to the bottom of the matter, ably assisted and hindered by her model friends. Cast also includes Ivana Milicevic, Shalom Harlow, Tomiko Fraser and China Chow.</p>", "description_for_label": ["<p>Australian supermodel Sarah O&#8217;Hare makes her acting debut as one of four models to share a plush Manhatten apartment with our protagonist, Amanda (Monica Potter). Single Amanda is cursed with dating the wrong men and when she spots handsome Jim Winston (Freddie Prinze Jr,) out her window - a man she met under curious circumstances in the lobby - she becomes instantly attracted and decidedly cautious. Under the guidance of her new flatmates, Amanda crashes a party at Jim&#8217;s and discovers he is almost too good to be true. Voyeurism wreaks havoc between the two soulmates when Amanda sees what she believes to be Jim committing a murder. When the police fail to locate a body she takes it upon herself to get to the bottom of the matter, ably assisted and hindered by her model friends. Cast also includes Ivana Milicevic, Shalom Harlow, Tomiko Fraser and China Chow.</p>"], "credit_line_for_label": "", "details": [{"label": "Duration", "display_values": ["01:22:00:00"]}, {"label": "Language", "display_values": ["English"]}, {"label": "Audience classification", "display_values": ["MA"]}, {"label": "Subject categories", "display_values": ["Comedy", "Crafts & Visual Arts&nbsp;→ Art objects - Conservation and restoration", "Crafts & Visual Arts&nbsp;→ Models, Fashion", "Family, Gender Identity, Relationships & Sexuality&nbsp;→ Dating (Social customs)", "Family, Gender Identity, Relationships & Sexuality&nbsp;→ Interpersonal conflict", "Family, Gender Identity, Relationships & Sexuality&nbsp;→ Shared housing", "Family, Gender Identity, Relationships & Sexuality&nbsp;→ Voyeurism", "Feature films", "Feature films&nbsp;→ Feature films - United States", "Food, Health, Lifestyle, Medicine, Psychology & Safety&nbsp;→ Interpersonal conflict", "Food, Health, Lifestyle, Medicine, Psychology & Safety&nbsp;→ Models, Fashion", "Food, Health, Lifestyle, Medicine, Psychology & Safety&nbsp;→ Shared housing", "Food, Health, Lifestyle, Medicine, Psychology & Safety&nbsp;→ Voyeurism", "Romance"]}, {"label": "Sound/audio", "display_values": ["Sound"]}, {"label": "Colour", "display_values": ["Colour"]}], "stats": {"tap_count": 0}, "links": [{"url": "https://www.justwatch.com/au/movie/head-over-heels-2001", "title": "Stream, rent or buy at <span>JustWatch</span>", "source": "justwatch"}], "creators_primary": [{"id": 1996792, "name": "Mark Waters", "creator_id": 31350, "creator_wikidata_id": "Q471552", "role": "director", "role_id": 938, "is_primary": true}, {"id": 1996791, "name": "Robert Simonds", "creator_id": 52080, "creator_wikidata_id": "Q731692", "role": "producer", "role_id": 1089, "is_primary": true}, {"id": 1996790, "name": "Universal Studios", "creator_id": 23708, "creator_wikidata_id": null, "role": "production company", "role_id": 941, "is_primary": true}], "creators_other": [{"id": 1996789, "name": "Universal Music Publishing", "creator_id": 78799, "creator_wikidata_id": null, "role": "distributor", "role_id": 437, "is_primary": false}], "media_note": "Sorry, we aren't able to make images or video for this item available to the public online.", "holdings": [{"name": "VHS; Access Print (Section 1)", "identifier": "", "description": ""}], "part_of": null, "parts": [], "part_siblings": [], "group": null, "group_works": [], "group_siblings": [], "source": {"name": "Vernon", "slug": "vernon"}, "source_identifier": "50377", "eaas_environment_id": null, "production_places": [{"id": 10, "name": "United Kingdom", "slug": "united-kingdom"}], "production_dates": [{"date": "2001", "notes": "Copyrighted", "to_year": "2001"}], "labels": [32353]}, {"id": 92861, "acmi_id": "316199", "title": "Save the lady", "title_annotation": "", "slug": "save-the-lady", "creator_credit": "Leon Thau, Barry Pierce and Tasmanian Film Corporation", "credit_line": "", "headline_credit": "Australia, 1981", "video_links": [], "record_type": "work", "type": "Film", "is_on_display": false, "last_on_display_place": null, "last_on_display_date": null, "is_context_indigenous": false, "material_description": "", "unpublished": false, "external": false, "first_production_date": "1981-01-01T11:00:00+11:00", "commissioned": false, "public_domain": false, "external_references": [{"id": 44031, "source": {"name": "Wikidata", "slug": "wikidata"}, "source_identifier": "Q7428108"}], "brief_description": "<p>A bunch of kids on hearing that a beloved steam ferry &#8220;The Lady Hope&#8221; has been decommissioned and due for the scrap heap decide to rescue the boat from destruction. They use the help from some of their adult allies to help rally against the government in an escalating and hilarious caper that promises to save the &#8216;Lady&#8217;. A child&#8217;s fantasy is saved when the kids command a string of well-hatched decoys to shrug off the threatening eyes of the government whilst restoring dignity to the historical boat. Includes footage of the city and bays around Hobart, Tasmania (Australia). Suitable for children 6-12 years.</p>", "constellations_primary": [], "constellations_other": [], "recommendations": [], "creator_credit_for_label": "<p>Leon Thau, Barry Pierce and Tasmanian Film Corporation</p>", "headline_credit_for_label": "<p>Australia, 1981</p>", "title_for_label": "<p>Save the lady</p>", "description": "<p>A bunch of kids on hearing that a beloved steam ferry &#8220;The Lady Hope&#8221; has been decommissioned and due for the scrap heap decide to rescue the boat from destruction. They use the help from some of their adult allies to help rally against the government in an escalating and hilarious caper that promises to save the &#8216;Lady&#8217;. A child&#8217;s fantasy is saved when the kids command a string of well-hatched decoys to shrug off the threatening eyes of the government whilst restoring dignity to the historical boat. Includes footage of the city and bays around Hobart, Tasmania (Australia). Suitable for children 6-12 years.</p>", "description_for_label": ["<p>A bunch of kids on hearing that a beloved steam ferry &#8220;The Lady Hope&#8221; has been decommissioned and due for the scrap heap decide to rescue the boat from destruction. They use the help from some of their adult allies to help rally against the government in an escalating and hilarious caper that promises to save the &#8216;Lady&#8217;. A child&#8217;s fantasy is saved when the kids command a string of well-hatched decoys to shrug off the threatening eyes of the government whilst restoring dignity to the historical boat. Includes footage of the city and bays around Hobart, Tasmania (Australia). Suitable for children 6-12 years.</p>"], "credit_line_for_label": "", "details": [{"label": "Duration", "display_values": ["01:53:00:00"]}, {"label": "Language", "display_values": ["English"]}, {"label": "Audience classification", "display_values": ["G"]}, {"label": "Subject categories", "display_values": ["Anthropology, Ethnology, Exploration & Travel&nbsp;→ Adventure and adventurers", "Anthropology, Ethnology, Exploration & Travel&nbsp;→ Children - Social life and customs", "Childrens Films", "Childrens Films&nbsp;→ Children 0-6", "Childrens Films&nbsp;→ Children 12+", "Childrens Films&nbsp;→ Children's films - Australia", "Communications, Infrastructure, & Transport&nbsp;→ River boats", "Communications, Infrastructure, & Transport&nbsp;→ Ships - Conservation and restoration", "Economics, Philosophy, Politics, Religion & Sociology&nbsp;→ Children - Social conditions", "Economics, Philosophy, Politics, Religion & Sociology&nbsp;→ Education of children", "Economics, Philosophy, Politics, Religion & Sociology&nbsp;→ Moral development in children", "Education, Instruction, Teaching & Schools&nbsp;→ Education of children", "Family, Gender Identity, Relationships & Sexuality&nbsp;→ Children - Family relationships", "Family, Gender Identity, Relationships & Sexuality&nbsp;→ Children - Social life and customs", "Family, Gender Identity, Relationships & Sexuality&nbsp;→ Education of children", "Family, Gender Identity, Relationships & Sexuality&nbsp;→ Emotions in children", "Family, Gender Identity, Relationships & Sexuality&nbsp;→ Moral development in children", "Family, Gender Identity, Relationships & Sexuality&nbsp;→ Self-reliance in children", "Feature films", "Feature films&nbsp;→ Feature films - Australia", "Food, Health, Lifestyle, Medicine, Psychology & Safety&nbsp;→ Moral development in children", "History&nbsp;→ Adventure and adventurers", "Literature&nbsp;→ Children's literature, Australian"]}, {"label": "Sound/audio", "display_values": ["Sound"]}, {"label": "Colour", "display_values": ["Colour"]}], "stats": {"tap_count": 0}, "links": [], "creators_primary": [{"id": 2263198, "name": "Leon Thau", "creator_id": 34567, "creator_wikidata_id": "Q6524917", "role": "director", "role_id": 938, "is_primary": true}, {"id": 2263193, "name": "Barry Pierce", "creator_id": 19395, "creator_wikidata_id": "Q20645617", "role": "producer", "role_id": 1089, "is_primary": true}, {"id": 2263189, "name": "Tasmanian Film Corporation", "creator_id": 12244, "creator_wikidata_id": null, "role": "production company", "role_id": 941, "is_primary": true}], "creators_other": [{"id": 2263184, "name": "Arts Centre Melbourne", "creator_id": 79926, "creator_wikidata_id": null, "role": "distributor", "role_id": 437, "is_primary": false}], "media_note": "Sorry, we don't have images or video for this item.", "holdings": [{"name": "VHS; Access Print (Section 1)", "identifier": "", "description": ""}], "part_of": null, "parts": [], "part_siblings": [], "group": null, "group_works": [], "group_siblings": [], "source": {"name": "Vernon", "slug": "vernon"}, "source_identifier": "50374", "eaas_environment_id": null, "production_places": [{"id": 3, "name": "Australia", "slug": "australia"}], "production_dates": [{"date": "1981", "notes": "Copyrighted", "to_year": "1981"}], "labels": [32351]}, {"id": 92860, "acmi_id": "316198", "title": "Stork", "title_annotation": "", "slug": "stork", "creator_credit": "Tim Burstall, Bilcock and Copping Film Productions and Tim Burstall and Associates", "credit_line": "", "headline_credit": "Australia, 1971", "video_links": [], "record_type": "work", "type": "Film", "is_on_display": false, "last_on_display_place": null, "last_on_display_date": null, "is_context_indigenous": false, "material_description": "", "unpublished": false, "external": false, "first_production_date": "1971-01-01T10:00:00+10:00", "commissioned": false, "public_domain": false, "external_references": [{"id": 52319, "source": {"name": "Wikidata", "slug": "wikidata"}, "source_identifier": "Q7620062"}], "brief_description": "<p>Adapted for the screen by David Williamson from his own stage play, Tim Burstall&#8217;s broad, low-budget comedy is one of the earliest, and most commercially successful, releases of the 1970s Australian film &#8216;renaissance&#8217;.</p>\n<p>The adventures of the seven-foot-tall, Marcuse-quoting, would-be-revolutionary &#8216;ocker&#8217;, Stork, (Bruce Spence) satirise many aspects of contemporary Australian society and values. &#8220;The targets of its humour are the social goals and values of the middle-classes - conformity, ambition, marriage, the pretensions of the corporate world or the academic and art establishments.&#8221; (Tim Burstall).</p>", "constellations_primary": [], "constellations_other": [], "recommendations": [], "creator_credit_for_label": "<p>Tim Burstall, Bilcock and Copping Film Productions and Tim Burstall and Associates</p>", "headline_credit_for_label": "<p>Australia, 1971</p>", "title_for_label": "<p>Stork</p>", "description": "<p>Adapted for the screen by David Williamson from his own stage play, Tim Burstall&#8217;s broad, low-budget comedy is one of the earliest, and most commercially successful, releases of the 1970s Australian film &#8216;renaissance&#8217;.</p>\n<p>The adventures of the seven-foot-tall, Marcuse-quoting, would-be-revolutionary &#8216;ocker&#8217;, Stork, (Bruce Spence) satirise many aspects of contemporary Australian society and values. &#8220;The targets of its humour are the social goals and values of the middle-classes - conformity, ambition, marriage, the pretensions of the corporate world or the academic and art establishments.&#8221; (Tim Burstall).</p>", "description_for_label": ["<p>Adapted for the screen by David Williamson from his own stage play, Tim Burstall&#8217;s broad, low-budget comedy is one of the earliest, and most commercially successful, releases of the 1970s Australian film &#8216;renaissance&#8217;.</p>\n<p>The adventures of the seven-foot-tall, Marcuse-quoting, would-be-revolutionary &#8216;ocker&#8217;, Stork, (Bruce Spence) satirise many aspects of contemporary Australian society and values. &#8220;The targets of its humour are the social goals and values of the middle-classes - conformity, ambition, marriage, the pretensions of the corporate world or the academic and art establishments.&#8221; (Tim Burstall).</p>"], "credit_line_for_label": "", "details": [{"label": "Duration", "display_values": ["01:26:02:00"]}, {"label": "Language", "display_values": ["English"]}, {"label": "Audience classifications", "display_values": ["MA", "Mediatheque - not for children (ACMI classified)"]}, {"label": "Subject categories", "display_values": ["Advertising, Film, Journalism, Mass Media & TV&nbsp;→ Motion pictures - Awards - Australia", "Advertising, Film, Journalism, Mass Media & TV&nbsp;→ Motion pictures, Australian", "Anthropology, Ethnology, Exploration & Travel&nbsp;→ National characteristics, Australian", "Comedy", "Comedy&nbsp;→ Slapstick comedies", "Economics, Philosophy, Politics, Religion & Sociology&nbsp;→ National characteristics, Australian", "Feature films", "Feature films&nbsp;→ Feature films - Australia", "Literature&nbsp;→ Australian wit and humor"]}, {"label": "Sound/audio", "display_values": ["Sound"]}, {"label": "Colour", "display_values": ["Colour"]}], "stats": {"tap_count": 0}, "links": [], "creators_primary": [{"id": 2314035, "name": "Tim Burstall", "creator_id": 66448, "creator_wikidata_id": "Q7803256", "role": "producer/director", "role_id": 31, "is_primary": true}, {"id": 2314025, "name": "Bilcock and Copping Film Productions", "creator_id": 19229, "creator_wikidata_id": "Q121091216", "role": "production company", "role_id": 941, "is_primary": true}, {"id": 2314017, "name": "Tim Burstall and Associates", "creator_id": 34564, "creator_wikidata_id": null, "role": "production company", "role_id": 941, "is_primary": true}], "creators_other": [{"id": 2314033, "name": "Experimental Film Fund, Australia Council for the Arts", "creator_id": 28084, "creator_wikidata_id": "Q121357763", "role": "associate producer", "role_id": 930, "is_primary": false}, {"id": 2314038, "name": "Bruce Spence", "creator_id": 76802, "creator_wikidata_id": "Q704314", "role": "cast", "role_id": 33, "is_primary": false}, {"id": 2314043, "name": "Graeme Blundell", "creator_id": 78021, "creator_wikidata_id": "Q5592208", "role": "cast", "role_id": 33, "is_primary": false}, {"id": 2314050, "name": "Helmut Bakaitis", "creator_id": 80024, "creator_wikidata_id": "Q972044", "role": "cast", "role_id": 33, "is_primary": false}, {"id": 2314041, "name": "Jacki Weaver", "creator_id": 73769, "creator_wikidata_id": "Q241897", "role": "cast", "role_id": 33, "is_primary": false}, {"id": 2314056, "name": "Jan Friedl", "creator_id": 78025, "creator_wikidata_id": "Q121035671", "role": "cast", "role_id": 33, "is_primary": false}, {"id": 2314061, "name": "Max Gillies", "creator_id": 76798, "creator_wikidata_id": "Q6794794", "role": "cast", "role_id": 33, "is_primary": false}, {"id": 2314054, "name": "Peter Cummins", "creator_id": 74740, "creator_wikidata_id": "Q7173470", "role": "cast", "role_id": 33, "is_primary": false}, {"id": 2314046, "name": "Sean McEuan", "creator_id": 80023, "creator_wikidata_id": "Q121315614", "role": "cast", "role_id": 33, "is_primary": false}, {"id": 2314064, "name": "Terry Norris", "creator_id": 74314, "creator_wikidata_id": "Q7704856", "role": "cast", "role_id": 33, "is_primary": false}, {"id": 2314014, "name": "Arts Centre Melbourne", "creator_id": 79926, "creator_wikidata_id": null, "role": "distributor", "role_id": 437, "is_primary": false}, {"id": 2314036, "name": "David Williamson", "creator_id": 76438, "creator_wikidata_id": "Q968980", "role": "screenwriter", "role_id": 601, "is_primary": false}], "media_note": null, "holdings": [{"name": "VHS; Preservation Print (Section 5)", "identifier": "", "description": ""}], "part_of": null, "parts": [], "part_siblings": [], "group": null, "group_works": [], "group_siblings": [], "source": {"name": "Vernon", "slug": "vernon"}, "source_identifier": "50373", "eaas_environment_id": null, "production_places": [{"id": 3, "name": "Australia", "slug": "australia"}], "production_dates": [{"date": "1971", "notes": "Produced", "to_year": "1971"}], "labels": [32350]}, {"id": 92858, "acmi_id": "316195", "title": "The Limey", "title_annotation": "", "slug": "the-limey", "creator_credit": "Steven Soderbergh, John Hardy, Scott Kramer and Artisan Pictures", "credit_line": "", "headline_credit": "United States, 1999", "video_links": [], "record_type": "work", "type": "Film", "is_on_display": false, "last_on_display_place": null, "last_on_display_date": null, "is_context_indigenous": false, "material_description": "", "unpublished": false, "external": false, "first_production_date": "1999-01-01T11:00:00+11:00", "commissioned": false, "public_domain": false, "external_references": [{"id": 23935, "source": {"name": "Wikidata", "slug": "wikidata"}, "source_identifier": "Q1382199"}], "brief_description": "<p>Steven Soderbergh&#8217;s &#8220;The Limey&#8221; is an understated revenge thriller which uses John Boorman&#8217;s stylistically daring, &#8220;Point blank&#8221; (1967) as its template. Terence Stamp&#8217;s stoic crim, Wilson, shares similar traits to Lee Marvin&#8217;s character in &#8220;Point blank&#8221;, mainly an unflinching determination and a blood thirsty drive for revenge. Fresh from the UK, recent ex-con Wilson lands in the sun drenched opulence of Los Angeles, when he receives news that his estranged daughter, Jenny (Melissa George), has perished in a car accident. Wilson learns that his daughter was seeing a wealthy record producer called Valentine (Peter Fonda), whose shady connections to the L.A. underworld make him suspect that his daughter&#8217;s death was no accident. Soderbergh takes much pleasure in placing the thuggish &#8216;fish out of water&#8217; Wilson in the middle of the trendy L.A. elite, while pitting two icons of the sixties, Stamp and Fonda against each other. The film&#8217;s themes of nostalgia and loss are cleverly realised in its complex editing structure which jumps back and forth through time, (this being &#8220;The Limey&#8217;s&#8221; most obvious nod to &#8220;Point blank&#8221;). Soderbergh however is also trading on a different kind of nostalgia by showcasing the acting talents of Terence Stamp, this loving homage accumulates in a scene from Ken Loach&#8217;s &#8220;Poor cow&#8221; (1968), (which starred a very young Stamp), a cherished film memory for Wilson and the audience alike. Cast includes: Lesley Ann Warren, Luis Guzman, Barry Newman, Joe Dallesandro.</p>", "constellations_primary": [], "constellations_other": [], "recommendations": [], "creator_credit_for_label": "<p>Steven Soderbergh, John Hardy, Scott Kramer and Artisan Pictures</p>", "headline_credit_for_label": "<p>United States, 1999</p>", "title_for_label": "<p>The Limey</p>", "description": "<p>Steven Soderbergh&#8217;s &#8220;The Limey&#8221; is an understated revenge thriller which uses John Boorman&#8217;s stylistically daring, &#8220;Point blank&#8221; (1967) as its template. Terence Stamp&#8217;s stoic crim, Wilson, shares similar traits to Lee Marvin&#8217;s character in &#8220;Point blank&#8221;, mainly an unflinching determination and a blood thirsty drive for revenge. Fresh from the UK, recent ex-con Wilson lands in the sun drenched opulence of Los Angeles, when he receives news that his estranged daughter, Jenny (Melissa George), has perished in a car accident. Wilson learns that his daughter was seeing a wealthy record producer called Valentine (Peter Fonda), whose shady connections to the L.A. underworld make him suspect that his daughter&#8217;s death was no accident. Soderbergh takes much pleasure in placing the thuggish &#8216;fish out of water&#8217; Wilson in the middle of the trendy L.A. elite, while pitting two icons of the sixties, Stamp and Fonda against each other. The film&#8217;s themes of nostalgia and loss are cleverly realised in its complex editing structure which jumps back and forth through time, (this being &#8220;The Limey&#8217;s&#8221; most obvious nod to &#8220;Point blank&#8221;). Soderbergh however is also trading on a different kind of nostalgia by showcasing the acting talents of Terence Stamp, this loving homage accumulates in a scene from Ken Loach&#8217;s &#8220;Poor cow&#8221; (1968), (which starred a very young Stamp), a cherished film memory for Wilson and the audience alike. Cast includes: Lesley Ann Warren, Luis Guzman, Barry Newman, Joe Dallesandro.</p>", "description_for_label": ["<p>Steven Soderbergh&#8217;s &#8220;The Limey&#8221; is an understated revenge thriller which uses John Boorman&#8217;s stylistically daring, &#8220;Point blank&#8221; (1967) as its template. Terence Stamp&#8217;s stoic crim, Wilson, shares similar traits to Lee Marvin&#8217;s character in &#8220;Point blank&#8221;, mainly an unflinching determination and a blood thirsty drive for revenge. Fresh from the UK, recent ex-con Wilson lands in the sun drenched opulence of Los Angeles, when he receives news that his estranged daughter, Jenny (Melissa George), has perished in a car accident. Wilson learns that his daughter was seeing a wealthy record producer called Valentine (Peter Fonda), whose shady connections to the L.A. underworld make him suspect that his daughter&#8217;s death was no accident. Soderbergh takes much pleasure in placing the thuggish &#8216;fish out of water&#8217; Wilson in the middle of the trendy L.A. elite, while pitting two icons of the sixties, Stamp and Fonda against each other. The film&#8217;s themes of nostalgia and loss are cleverly realised in its complex editing structure which jumps back and forth through time, (this being &#8220;The Limey&#8217;s&#8221; most obvious nod to &#8220;Point blank&#8221;). Soderbergh however is also trading on a different kind of nostalgia by showcasing the acting talents of Terence Stamp, this loving homage accumulates in a scene from Ken Loach&#8217;s &#8220;Poor cow&#8221; (1968), (which starred a very young Stamp), a cherished film memory for Wilson and the audience alike. Cast includes: Lesley Ann Warren, Luis Guzman, Barry Newman, Joe Dallesandro.</p>"], "credit_line_for_label": "", "details": [{"label": "Duration", "display_values": ["01:25:00:00"]}, {"label": "Language", "display_values": ["English"]}, {"label": "Audience classification", "display_values": ["M (15+)"]}, {"label": "Subject categories", "display_values": ["Courtroom, Crime, Espionage & Thrillers", "Courtroom, Crime, Espionage & Thrillers&nbsp;→ Crime films", "Courtroom, Crime, Espionage & Thrillers&nbsp;→ Thrillers", "Crime, Espionage, Justice, Police & Prisons&nbsp;→ Organized crime - United States", "Family, Gender Identity, Relationships & Sexuality&nbsp;→ Fathers and daughters", "Feature films", "Feature films&nbsp;→ Feature films - United States", "Food, Health, Lifestyle, Medicine, Psychology & Safety&nbsp;→ Revenge"]}, {"label": "Sound/audio", "display_values": ["Sound"]}, {"label": "Colour", "display_values": ["Colour"]}], "stats": {"tap_count": 0}, "links": [{"url": "https://www.justwatch.com/au/movie/the-limey", "title": "Stream, rent or buy at <span>JustWatch</span>", "source": "justwatch"}], "creators_primary": [{"id": 1996783, "name": "Steven Soderbergh", "creator_id": 68097, "creator_wikidata_id": "Q103917", "role": "director", "role_id": 938, "is_primary": true}, {"id": 1996781, "name": "John Hardy", "creator_id": 77367, "creator_wikidata_id": "Q121078961", "role": "co-producer", "role_id": 915, "is_primary": true}, {"id": 1996782, "name": "Scott Kramer", "creator_id": 80020, "creator_wikidata_id": "Q121036851", "role": "co-producer", "role_id": 915, "is_primary": true}, {"id": 1996780, "name": "Artisan Pictures", "creator_id": 34560, "creator_wikidata_id": null, "role": "production company", "role_id": 941, "is_primary": true}], "creators_other": [], "media_note": "Sorry, we aren't able to make images or video for this item available to the public online.", "holdings": [{"name": "VHS; Access Print (Section 1)", "identifier": "", "description": ""}], "part_of": null, "parts": [], "part_siblings": [], "group": null, "group_works": [], "group_siblings": [], "source": {"name": "Vernon", "slug": "vernon"}, "source_identifier": "50371", "eaas_environment_id": null, "production_places": [{"id": 2, "name": "United States", "slug": "united-states"}], "production_dates": [{"date": "1999", "notes": "Copyrighted", "to_year": "1999"}], "labels": [32348]}, {"id": 92857, "acmi_id": "316194", "title": "Jack's back", "title_annotation": "", "slug": "jacks-back", "creator_credit": "Rowdy Herrington, Cassian Elwes, Tim Moore and Palisades Entertainment Group", "credit_line": "", "headline_credit": "United States, 1988", "video_links": [], "record_type": "work", "type": "Film", "is_on_display": false, "last_on_display_place": null, "last_on_display_date": null, "is_context_indigenous": false, "material_description": "", "unpublished": false, "external": false, "first_production_date": "1988-01-01T11:00:00+11:00", "commissioned": false, "public_domain": false, "external_references": [{"id": 46655, "source": {"name": "Wikidata", "slug": "wikidata"}, "source_identifier": "Q646372"}], "brief_description": "<p>It is August 1988, one hundred years since Jack the Ripper committed his brutal murders in the East End of London and now Los Angeles finds itself experiencing that very same fear as a copy-cat &#8220;Jack the Ripper&#8221; is on the loose, stalking the streets and murdering his prostitute victims in the same cold and calculated manner as his predecessor one hundred years ago. However in this tale, there is an unusual twist to the plot involving a young physician (James Spader) and his twin brother. Cast includes Cynthia Gibb, Jim Haynie, Robert Picardo and Rod Loomis.</p>", "constellations_primary": [], "constellations_other": [], "recommendations": [], "creator_credit_for_label": "<p>Rowdy Herrington, Cassian Elwes, Tim Moore and Palisades Entertainment Group</p>", "headline_credit_for_label": "<p>United States, 1988</p>", "title_for_label": "<p>Jack&#8217;s back</p>", "description": "<p>It is August 1988, one hundred years since Jack the Ripper committed his brutal murders in the East End of London and now Los Angeles finds itself experiencing that very same fear as a copy-cat &#8220;Jack the Ripper&#8221; is on the loose, stalking the streets and murdering his prostitute victims in the same cold and calculated manner as his predecessor one hundred years ago. However in this tale, there is an unusual twist to the plot involving a young physician (James Spader) and his twin brother. Cast includes Cynthia Gibb, Jim Haynie, Robert Picardo and Rod Loomis.</p>", "description_for_label": ["<p>It is August 1988, one hundred years since Jack the Ripper committed his brutal murders in the East End of London and now Los Angeles finds itself experiencing that very same fear as a copy-cat &#8220;Jack the Ripper&#8221; is on the loose, stalking the streets and murdering his prostitute victims in the same cold and calculated manner as his predecessor one hundred years ago. However in this tale, there is an unusual twist to the plot involving a young physician (James Spader) and his twin brother. Cast includes Cynthia Gibb, Jim Haynie, Robert Picardo and Rod Loomis.</p>"], "credit_line_for_label": "", "details": [{"label": "Duration", "display_values": ["01:32:00:00"]}, {"label": "Language", "display_values": ["English"]}, {"label": "Audience classification", "display_values": ["R (18+)"]}, {"label": "Subject categories", "display_values": ["Courtroom, Crime, Espionage & Thrillers", "Courtroom, Crime, Espionage & Thrillers&nbsp;→ Crime films", "Courtroom, Crime, Espionage & Thrillers&nbsp;→ Detective and mystery films", "Courtroom, Crime, Espionage & Thrillers&nbsp;→ Thrillers", "Crime, Espionage, Justice, Police & Prisons&nbsp;→ Serial murderers", "Feature films", "Feature films&nbsp;→ Feature films - United States"]}, {"label": "Sound/audio", "display_values": ["Sound"]}, {"label": "Colour", "display_values": ["Colour"]}], "stats": {"tap_count": 0}, "links": [{"url": "https://www.justwatch.com/au/movie/jacks-back", "title": "Stream, rent or buy at <span>JustWatch</span>", "source": "justwatch"}], "creators_primary": [{"id": 2162722, "name": "Rowdy Herrington", "creator_id": 34559, "creator_wikidata_id": "Q3445566", "role": "director", "role_id": 938, "is_primary": true}, {"id": 2162720, "name": "Cassian Elwes", "creator_id": 80019, "creator_wikidata_id": "Q5049340", "role": "co-producer", "role_id": 915, "is_primary": true}, {"id": 2162717, "name": "Tim Moore", "creator_id": 80018, "creator_wikidata_id": "Q121298759", "role": "co-producer", "role_id": 915, "is_primary": true}, {"id": 2162716, "name": "Palisades Entertainment Group", "creator_id": 34556, "creator_wikidata_id": "Q121034338", "role": "production company", "role_id": 941, "is_primary": true}], "creators_other": [], "media_note": "Sorry, we aren't able to make images or video for this item available to the public online.", "holdings": [{"name": "VHS; Access Print (Section 1)", "identifier": "", "description": ""}], "part_of": null, "parts": [], "part_siblings": [], "group": null, "group_works": [], "group_siblings": [], "source": {"name": "Vernon", "slug": "vernon"}, "source_identifier": "50370", "eaas_environment_id": null, "production_places": [{"id": 2, "name": "United States", "slug": "united-states"}], "production_dates": [{"date": "1988", "notes": "Copyrighted", "to_year": "1988"}], "labels": [32347]}, {"id": 92856, "acmi_id": "316193", "title": "Vagabond = Sans toit ni loi", "title_annotation": "", "slug": "vagabond-sans-toit-ni-loi", "creator_credit": "Agnes Varda, Oury Milshtein, Channel 4, Cine Tamaris and French Ministry of Culture", "credit_line": "", "headline_credit": "France, 1985", "video_links": [], "record_type": "work", "type": "Film", "is_on_display": false, "last_on_display_place": null, "last_on_display_date": null, "is_context_indigenous": false, "material_description": "", "unpublished": false, "external": false, "first_production_date": "1985-01-01T11:00:00+11:00", "commissioned": false, "public_domain": false, "external_references": [{"id": 540, "source": {"name": "Wikidata", "slug": "wikidata"}, "source_identifier": "Q2298257"}], "brief_description": "<p>Vagabond (Sans Toit Ni Loi) is considered by many to be one of Agnes Varda&#8217;s finest works and a classic of the nouvelle vague tradition of filmmaking. This is a coldly beautiful film that tells the story of Mona (Sandrine Bonnaire), a wanderer who moves from town to town living in her tent or with whoever will take her in. The film opens with Mona&#8217;s frozen body found lying in a ditch and proceeds to trace her story in a series of flashbacks to the point of her death. Bonnaire gives an impressive performance of the cold, and not completely likeable Mona, who remains distant to the people she meets and also the audience. Her distance intrigues on many levels. She talks of hoping to one day own a piece of land, and then later wishes to be the caretaker of a house. Given the opportunity for both, she moves on, seemingly unable to live anything but a nomadic existence. Rather than being a free spirit living a romanticised life free of society&#8217;s chains, Mona&#8217;s existence seems meaningless and emotionally void. Varda&#8217;s early career as a photographer is evident in her use of elegant framing and striking spacialization. The film won the Golden Lion at the Venice Film Festival and earned Sandrine Bonnaire a French Cesar award. Pauline Kael describes Varda thus: &#8220;A full-fledged visual filmmaker&#8230;Varda sustains an unsentimental yet subjective tone that is almost unique in the history of movies&#8221;. In French with English subtitles.</p>", "constellations_primary": [], "constellations_other": [], "recommendations": [], "creator_credit_for_label": "<p>Agnes Varda, Oury Milshtein, Channel 4, Cine Tamaris and French Ministry of Culture</p>", "headline_credit_for_label": "<p>France, 1985</p>", "title_for_label": "<p>Vagabond = Sans toit ni loi</p>", "description": "<p>Vagabond (Sans Toit Ni Loi) is considered by many to be one of Agnes Varda&#8217;s finest works and a classic of the nouvelle vague tradition of filmmaking. This is a coldly beautiful film that tells the story of Mona (Sandrine Bonnaire), a wanderer who moves from town to town living in her tent or with whoever will take her in. The film opens with Mona&#8217;s frozen body found lying in a ditch and proceeds to trace her story in a series of flashbacks to the point of her death. Bonnaire gives an impressive performance of the cold, and not completely likeable Mona, who remains distant to the people she meets and also the audience. Her distance intrigues on many levels. She talks of hoping to one day own a piece of land, and then later wishes to be the caretaker of a house. Given the opportunity for both, she moves on, seemingly unable to live anything but a nomadic existence. Rather than being a free spirit living a romanticised life free of society&#8217;s chains, Mona&#8217;s existence seems meaningless and emotionally void. Varda&#8217;s early career as a photographer is evident in her use of elegant framing and striking spacialization. The film won the Golden Lion at the Venice Film Festival and earned Sandrine Bonnaire a French Cesar award. Pauline Kael describes Varda thus: &#8220;A full-fledged visual filmmaker&#8230;Varda sustains an unsentimental yet subjective tone that is almost unique in the history of movies&#8221;. In French with English subtitles.</p>", "description_for_label": ["<p>Vagabond (Sans Toit Ni Loi) is considered by many to be one of Agnes Varda&#8217;s finest works and a classic of the nouvelle vague tradition of filmmaking. This is a coldly beautiful film that tells the story of Mona (Sandrine Bonnaire), a wanderer who moves from town to town living in her tent or with whoever will take her in. The film opens with Mona&#8217;s frozen body found lying in a ditch and proceeds to trace her story in a series of flashbacks to the point of her death. Bonnaire gives an impressive performance of the cold, and not completely likeable Mona, who remains distant to the people she meets and also the audience. Her distance intrigues on many levels. She talks of hoping to one day own a piece of land, and then later wishes to be the caretaker of a house. Given the opportunity for both, she moves on, seemingly unable to live anything but a nomadic existence. Rather than being a free spirit living a romanticised life free of society&#8217;s chains, Mona&#8217;s existence seems meaningless and emotionally void. Varda&#8217;s early career as a photographer is evident in her use of elegant framing and striking spacialization. The film won the Golden Lion at the Venice Film Festival and earned Sandrine Bonnaire a French Cesar award. Pauline Kael describes Varda thus: &#8220;A full-fledged visual filmmaker&#8230;Varda sustains an unsentimental yet subjective tone that is almost unique in the history of movies&#8221;. In French with English subtitles.</p>"], "credit_line_for_label": "", "details": [{"label": "Duration", "display_values": ["01:41:00:00"]}, {"label": "Languages", "display_values": ["English", "French"]}, {"label": "Audience classification", "display_values": ["MA"]}, {"label": "Subject categories", "display_values": ["Advertising, Film, Journalism, Mass Media & TV&nbsp;→ Foreign language films", "Economics, Philosophy, Politics, Religion & Sociology&nbsp;→ Homeless persons", "Economics, Philosophy, Politics, Religion & Sociology&nbsp;→ Homelessness", "Feature films", "Feature films&nbsp;→ Feature films - France", "Food, Health, Lifestyle, Medicine, Psychology & Safety&nbsp;→ Women - Psychology", "Foreign language films"]}, {"label": "Sound/audio", "display_values": ["Sound"]}, {"label": "Colour", "display_values": ["Colour"]}], "stats": {"tap_count": 0}, "links": [], "creators_primary": [{"id": 813165, "name": "Agnes Varda", "creator_id": 34373, "creator_wikidata_id": "Q229990", "role": "director", "role_id": 938, "is_primary": true}, {"id": 1805476, "name": "Oury Milshtein", "creator_id": 34555, "creator_wikidata_id": "Q3358488", "role": "producer", "role_id": 1089, "is_primary": true}, {"id": 813161, "name": "Channel 4", "creator_id": 21799, "creator_wikidata_id": "Q501070", "role": "production company", "role_id": 941, "is_primary": true}, {"id": 813162, "name": "Cine Tamaris", "creator_id": 34553, "creator_wikidata_id": null, "role": "production company", "role_id": 941, "is_primary": true}, {"id": 813163, "name": "French Ministry of Culture", "creator_id": 34554, "creator_wikidata_id": null, "role": "production company", "role_id": 941, "is_primary": true}], "creators_other": [], "media_note": "Sorry, we don't have images or video for this item.", "holdings": [{"name": "VHS; Access Print (Section 1)", "identifier": "", "description": ""}], "part_of": null, "parts": [], "part_siblings": [], "group": null, "group_works": [], "group_siblings": [], "source": {"name": "Vernon", "slug": "vernon"}, "source_identifier": "50369", "eaas_environment_id": null, "production_places": [{"id": 17, "name": "France", "slug": "france"}], "production_dates": [{"date": "1985", "notes": "Copyrighted", "to_year": "1985"}], "labels": [32346]}, {"id": 92854, "acmi_id": "316191", "title": "Carry on sergeant", "title_annotation": "", "slug": "carry-on-sergeant", "creator_credit": "Gerald Thomas, Peter Rogers and Nat Cohen and Stuart Levy Productions", "credit_line": "", "headline_credit": "United Kingdom, 1958", "video_links": [], "record_type": "work", "type": "Film", "is_on_display": false, "last_on_display_place": null, "last_on_display_date": null, "is_context_indigenous": false, "material_description": "", "unpublished": false, "external": false, "first_production_date": "1958-01-01T10:00:00+10:00", "commissioned": false, "public_domain": false, "external_references": [{"id": 43729, "source": {"name": "Wikidata", "slug": "wikidata"}, "source_identifier": "Q1489818"}], "brief_description": "<p>Episode number 1 of Series &#8220;Carry on&#8221;.<br />\nOn the eve of retirement Sergeant Grimshaw (William Hartnell) hopes, with the arrival of his new and last National Service recruits, to retire with the honour of winning the Star Squad prize. His plans are tested when the recruits show themselves to be a motley crew of prankish misfits. The first in the Carry On series is a bright wartime comical farce. With only a few of the regular Carry On crew we see Kenneth Williams (as James Bailey) in one of his funniest performances. Cast also includes: Shirley Eaton, Eric Barker, Dora Bryan, Bill Owen, Charles Hawtrey, Kenneth Connor, Terence Longdon, Norman Rossington, Gerald Campion, Hattie Jacques, Cyril Chamberlain, Arnold Diamond and Gordon Tanner.</p>", "constellations_primary": [], "constellations_other": [], "recommendations": [], "creator_credit_for_label": "<p>Gerald Thomas, Peter Rogers and Nat Cohen and Stuart Levy Productions</p>", "headline_credit_for_label": "<p>United Kingdom, 1958</p>", "title_for_label": "<p>Carry on sergeant</p>", "description": "<p>Episode number 1 of Series &#8220;Carry on&#8221;.<br />\nOn the eve of retirement Sergeant Grimshaw (William Hartnell) hopes, with the arrival of his new and last National Service recruits, to retire with the honour of winning the Star Squad prize. His plans are tested when the recruits show themselves to be a motley crew of prankish misfits. The first in the Carry On series is a bright wartime comical farce. With only a few of the regular Carry On crew we see Kenneth Williams (as James Bailey) in one of his funniest performances. Cast also includes: Shirley Eaton, Eric Barker, Dora Bryan, Bill Owen, Charles Hawtrey, Kenneth Connor, Terence Longdon, Norman Rossington, Gerald Campion, Hattie Jacques, Cyril Chamberlain, Arnold Diamond and Gordon Tanner.</p>", "description_for_label": ["<p>Episode number 1 of Series &#8220;Carry on&#8221;.<br />\nOn the eve of retirement Sergeant Grimshaw (William Hartnell) hopes, with the arrival of his new and last National Service recruits, to retire with the honour of winning the Star Squad prize. His plans are tested when the recruits show themselves to be a motley crew of prankish misfits. The first in the Carry On series is a bright wartime comical farce. With only a few of the regular Carry On crew we see Kenneth Williams (as James Bailey) in one of his funniest performances. Cast also includes: Shirley Eaton, Eric Barker, Dora Bryan, Bill Owen, Charles Hawtrey, Kenneth Connor, Terence Longdon, Norman Rossington, Gerald Campion, Hattie Jacques, Cyril Chamberlain, Arnold Diamond and Gordon Tanner.</p>"], "credit_line_for_label": "", "details": [{"label": "Duration", "display_values": ["01:20:00:00"]}, {"label": "Language", "display_values": ["English"]}, {"label": "Audience classification", "display_values": ["G"]}, {"label": "Subject categories", "display_values": ["Armed Forces, Military, War & Weapons&nbsp;→ Military camps", "Armed Forces, Military, War & Weapons&nbsp;→ Military discipline", "Armed Forces, Military, War & Weapons&nbsp;→ Military life", "Comedy", "Comedy&nbsp;→ Farce", "Family, Gender Identity, Relationships & Sexuality&nbsp;→ Sexual attraction", "Feature films", "Feature films&nbsp;→ Feature films - Great Britain"]}, {"label": "Sound/audio", "display_values": ["Sound"]}, {"label": "Colour", "display_values": ["Black and White"]}], "stats": {"tap_count": 0}, "links": [], "creators_primary": [{"id": 2245902, "name": "Gerald Thomas", "creator_id": 25067, "creator_wikidata_id": "Q740649", "role": "director", "role_id": 938, "is_primary": true}, {"id": 2245899, "name": "Peter Rogers", "creator_id": 25066, "creator_wikidata_id": "Q715904", "role": "producer", "role_id": 1089, "is_primary": true}, {"id": 2245898, "name": "Nat Cohen and Stuart Levy Productions", "creator_id": 34552, "creator_wikidata_id": "Q121143778", "role": "production company", "role_id": 941, "is_primary": true}], "creators_other": [], "media_note": "Sorry, we aren't able to make images or video for this item available to the public online.", "holdings": [{"name": "VHS; Access Print (Section 1)", "identifier": "", "description": ""}], "part_of": null, "parts": [], "part_siblings": [], "group": {"id": 115530, "acmi_id": "S01357", "title": "Carry on", "title_annotation": "", "slug": "carry-on", "creator_credit": "Gerald Thomas, Peter Rogers, Adder Productions and Rank Organisation Film Productions", "credit_line": "", "headline_credit": "United Kingdom", "video_links": [], "record_type": "group", "type": "Film", "is_on_display": false, "last_on_display_place": null, "last_on_display_date": null, "is_context_indigenous": false, "material_description": "", "unpublished": false, "external": false, "first_production_date": null, "commissioned": false, "public_domain": false, "external_references": [{"id": 53504, "source": {"name": "Wikidata", "slug": "wikidata"}, "source_identifier": "Q948916"}]}, "group_works": [], "group_siblings": [{"id": 89035, "acmi_id": "311661", "title": "Carry on abroad: or, what a package: or, it's all in: or, Swiss hols in the snow", "title_annotation": "", "slug": "carry-on-abroad-or-what-a-package-or-its-all-in-or-swiss-hols-in-the-snow", "creator_credit": "Gerald Thomas, Peter Rogers and Rank Organisation Film Productions", "credit_line": "", "headline_credit": "United Kingdom, 1972", "video_links": [], "record_type": "work", "type": "Film", "is_on_display": false, "last_on_display_place": null, "last_on_display_date": null, "is_context_indigenous": false, "material_description": "", "unpublished": false, "external": false, "first_production_date": "1972-01-01T11:00:00+11:00", "commissioned": false, "public_domain": false, "external_references": []}, {"id": 92984, "acmi_id": "316341", "title": "Carry on camping = Let sleeping bags lie", "title_annotation": "", "slug": "carry-on-camping-let-sleeping-bags-lie", "creator_credit": "Gerald Thomas, Peter Rogers, Adder Productions and Rank Organisation Film Productions", "credit_line": "", "headline_credit": "United Kingdom, 1969", "video_links": [], "record_type": "work", "type": "Film", "is_on_display": false, "last_on_display_place": null, "last_on_display_date": null, "is_context_indigenous": false, "material_description": "", "unpublished": false, "external": false, "first_production_date": "1969-01-01T10:00:00+10:00", "commissioned": false, "public_domain": false, "external_references": [{"id": 44309, "source": {"name": "Wikidata", "slug": "wikidata"}, "source_identifier": "Q449207"}]}, {"id": 92940, "acmi_id": "316282", "title": "Carry on constable", "title_annotation": "", "slug": "carry-on-constable", "creator_credit": "Gerald Thomas, Peter Rogers and Peter Rogers Productions", "credit_line": "", "headline_credit": "United Kingdom, 1961", "video_links": [], "record_type": "work", "type": "Film", "is_on_display": false, "last_on_display_place": null, "last_on_display_date": null, "is_context_indigenous": false, "material_description": "", "unpublished": false, "external": false, "first_production_date": "1961-01-01T10:00:00+10:00", "commissioned": false, "public_domain": false, "external_references": [{"id": 47991, "source": {"name": "Wikidata", "slug": "wikidata"}, "source_identifier": "Q1325568"}]}, {"id": 89037, "acmi_id": "311663", "title": "Carry on Dick", "title_annotation": "", "slug": "carry-on-dick", "creator_credit": "Gerald Thomas, Peter Rogers and Rank Organisation Film Productions", "credit_line": "", "headline_credit": "United Kingdom, 1974", "video_links": [], "record_type": "work", "type": "Film", "is_on_display": false, "last_on_display_place": null, "last_on_display_date": null, "is_context_indigenous": false, "material_description": "", "unpublished": false, "external": false, "first_production_date": "1974-01-01T11:00:00+11:00", "commissioned": false, "public_domain": false, "external_references": [{"id": 47126, "source": {"name": "Wikidata", "slug": "wikidata"}, "source_identifier": "Q302927"}]}, {"id": 89034, "acmi_id": "311660", "title": "Carry on doctor", "title_annotation": "", "slug": "carry-on-doctor", "creator_credit": "Gerald Thomas, Peter Rogers and Rank Organisation Film Productions", "credit_line": "", "headline_credit": "United Kingdom, 1967", "video_links": [], "record_type": "work", "type": "Film", "is_on_display": false, "last_on_display_place": null, "last_on_display_date": null, "is_context_indigenous": false, "material_description": "", "unpublished": false, "external": false, "first_production_date": "1967-01-01T10:00:00+10:00", "commissioned": false, "public_domain": false, "external_references": [{"id": 44774, "source": {"name": "Wikidata", "slug": "wikidata"}, "source_identifier": "Q179508"}]}, {"id": 82933, "acmi_id": "325383", "title": "Carry on doctor (Captioned)", "title_annotation": "", "slug": "carry-on-doctor-captioned", "creator_credit": "Gerald Thomas, Peter Rogers and Rank Organisation Film Productions", "credit_line": "", "headline_credit": "United Kingdom, 1967", "video_links": [], "record_type": "work", "type": "Film", "is_on_display": false, "last_on_display_place": null, "last_on_display_date": null, "is_context_indigenous": false, "material_description": "", "unpublished": false, "external": false, "first_production_date": "1967-01-01T10:00:00+10:00", "commissioned": false, "public_domain": false, "external_references": [{"id": 44245, "source": {"name": "Wikidata", "slug": "wikidata"}, "source_identifier": "Q179508"}]}, {"id": 92983, "acmi_id": "316340", "title": "Carry on Henry = Mind my chopper", "title_annotation": "", "slug": "carry-on-henry-mind-my-chopper", "creator_credit": "Gerald Thomas, Peter Rogers and Adder Productions", "credit_line": "", "headline_credit": "United Kingdom, 1970", "video_links": [], "record_type": "work", "type": "Film", "is_on_display": false, "last_on_display_place": null, "last_on_display_date": null, "is_context_indigenous": false, "material_description": "", "unpublished": false, "external": false, "first_production_date": "1970-01-01T10:00:00+10:00", "commissioned": false, "public_domain": false, "external_references": [{"id": 47111, "source": {"name": "Wikidata", "slug": "wikidata"}, "source_identifier": "Q449222"}]}, {"id": 92853, "acmi_id": "316190", "title": "Carry on screaming", "title_annotation": "", "slug": "carry-on-screaming", "creator_credit": "Gerald Thomas and Peter Rogers", "credit_line": "", "headline_credit": "United Kingdom, 1966", "video_links": [], "record_type": "work", "type": "Film", "is_on_display": false, "last_on_display_place": null, "last_on_display_date": null, "is_context_indigenous": false, "material_description": "", "unpublished": false, "external": false, "first_production_date": "1966-01-01T10:00:00+10:00", "commissioned": false, "public_domain": false, "external_references": [{"id": 45061, "source": {"name": "Wikidata", "slug": "wikidata"}, "source_identifier": "Q1674804"}]}, {"id": 89036, "acmi_id": "311662", "title": "Carry on up the Khyber", "title_annotation": "", "slug": "carry-on-up-the-khyber", "creator_credit": "Gerald Thomas, Peter Rogers, Peter Rogers Productions and Rank Film Productions", "credit_line": "", "headline_credit": "United Kingdom, 1968", "video_links": [], "record_type": "work", "type": "Film", "is_on_display": false, "last_on_display_place": null, "last_on_display_date": null, "is_context_indigenous": false, "material_description": "", "unpublished": false, "external": false, "first_production_date": "1968-01-01T10:00:00+10:00", "commissioned": false, "public_domain": false, "external_references": [{"id": 46427, "source": {"name": "Wikidata", "slug": "wikidata"}, "source_identifier": "Q448090"}]}, {"id": 82934, "acmi_id": "325384", "title": "Carry on up the Khyber (Captioned)", "title_annotation": "", "slug": "carry-on-up-the-khyber-captioned", "creator_credit": "Gerald Thomas, Peter Rogers, Peter Rogers Productions and Rank Film Productions", "credit_line": "", "headline_credit": "United Kingdom, 1968", "video_links": [], "record_type": "work", "type": "Film", "is_on_display": false, "last_on_display_place": null, "last_on_display_date": null, "is_context_indigenous": false, "material_description": "", "unpublished": false, "external": false, "first_production_date": "1968-01-01T10:00:00+10:00", "commissioned": false, "public_domain": false, "external_references": [{"id": 46832, "source": {"name": "Wikidata", "slug": "wikidata"}, "source_identifier": "Q448090"}]}, {"id": 92985, "acmi_id": "316342", "title": "Don't lose your head", "title_annotation": "", "slug": "dont-lose-your-head", "creator_credit": "Gerald Thomas, Peter Rogers and Adder Productions", "credit_line": "", "headline_credit": "United Kingdom, 1966", "video_links": [], "record_type": "work", "type": "Film", "is_on_display": false, "last_on_display_place": null, "last_on_display_date": null, "is_context_indigenous": false, "material_description": "", "unpublished": false, "external": false, "first_production_date": "1966-01-01T10:00:00+10:00", "commissioned": false, "public_domain": false, "external_references": [{"id": 44758, "source": {"name": "Wikidata", "slug": "wikidata"}, "source_identifier": "Q1538005"}]}, {"id": 92986, "acmi_id": "316343", "title": "Follow that camel", "title_annotation": "", "slug": "follow-that-camel", "creator_credit": "Gerald Thomas, Peter Rogers and Peter Rogers Productions", "credit_line": "", "headline_credit": "United Kingdom, 1967", "video_links": [], "record_type": "work", "type": "Film", "is_on_display": false, "last_on_display_place": null, "last_on_display_date": null, "is_context_indigenous": false, "material_description": "", "unpublished": false, "external": false, "first_production_date": "1967-01-01T10:00:00+10:00", "commissioned": false, "public_domain": false, "external_references": [{"id": 46284, "source": {"name": "Wikidata", "slug": "wikidata"}, "source_identifier": "Q1674807"}]}], "source": {"name": "Vernon", "slug": "vernon"}, "source_identifier": "50367", "eaas_environment_id": null, "production_places": [{"id": 10, "name": "United Kingdom", "slug": "united-kingdom"}], "production_dates": [{"date": "1958", "notes": "Copyrighted", "to_year": "1958"}], "labels": [32344]}, {"id": 92853, "acmi_id": "316190", "title": "Carry on screaming", "title_annotation": "", "slug": "carry-on-screaming", "creator_credit": "Gerald Thomas and Peter Rogers", "credit_line": "", "headline_credit": "United Kingdom, 1966", "video_links": [], "record_type": "work", "type": "Film", "is_on_display": false, "last_on_display_place": null, "last_on_display_date": null, "is_context_indigenous": false, "material_description": "", "unpublished": false, "external": false, "first_production_date": "1966-01-01T10:00:00+10:00", "commissioned": false, "public_domain": false, "external_references": [{"id": 45061, "source": {"name": "Wikidata", "slug": "wikidata"}, "source_identifier": "Q1674804"}], "brief_description": "<p>Episode of Series &#8220;Carry on&#8221;.<br />\nA virgin goes missing in the woods in this &#8216;Carry on&#8217; spoof, leaving her boyfriend and two hopeless detectives in search of her. Their only clue is the remaining gruesome finger of a &#8220;homo-garganturoso&#8221; (an extinct hairy man) at the scene of the crime. They happen upon a spooky house, complete with expressionless butler, buxom vamp and an undead master of the house. When the lost finger is subjected to an electrical charge, another large hairy man is generated. Why does the mannequin resemble the missing girl and what is the vitrification process? The horror theme is made complete with the usual toilet humour and innuendo of the &#8216;Carry on&#8217; crew. Cast includes Harry H. Corbett, Kenneth Williams and Joan Sims.</p>", "constellations_primary": [], "constellations_other": [], "recommendations": [], "creator_credit_for_label": "<p>Gerald Thomas and Peter Rogers</p>", "headline_credit_for_label": "<p>United Kingdom, 1966</p>", "title_for_label": "<p>Carry on screaming</p>", "description": "<p>Episode of Series &#8220;Carry on&#8221;.<br />\nA virgin goes missing in the woods in this &#8216;Carry on&#8217; spoof, leaving her boyfriend and two hopeless detectives in search of her. Their only clue is the remaining gruesome finger of a &#8220;homo-garganturoso&#8221; (an extinct hairy man) at the scene of the crime. They happen upon a spooky house, complete with expressionless butler, buxom vamp and an undead master of the house. When the lost finger is subjected to an electrical charge, another large hairy man is generated. Why does the mannequin resemble the missing girl and what is the vitrification process? The horror theme is made complete with the usual toilet humour and innuendo of the &#8216;Carry on&#8217; crew. Cast includes Harry H. Corbett, Kenneth Williams and Joan Sims.</p>", "description_for_label": ["<p>Episode of Series &#8220;Carry on&#8221;.<br />\nA virgin goes missing in the woods in this &#8216;Carry on&#8217; spoof, leaving her boyfriend and two hopeless detectives in search of her. Their only clue is the remaining gruesome finger of a &#8220;homo-garganturoso&#8221; (an extinct hairy man) at the scene of the crime. They happen upon a spooky house, complete with expressionless butler, buxom vamp and an undead master of the house. When the lost finger is subjected to an electrical charge, another large hairy man is generated. Why does the mannequin resemble the missing girl and what is the vitrification process? The horror theme is made complete with the usual toilet humour and innuendo of the &#8216;Carry on&#8217; crew. Cast includes Harry H. Corbett, Kenneth Williams and Joan Sims.</p>"], "credit_line_for_label": "", "details": [{"label": "Duration", "display_values": ["01:32:00:00"]}, {"label": "Language", "display_values": ["English"]}, {"label": "Audience classification", "display_values": ["PG"]}, {"label": "Subject categories", "display_values": ["Comedy", "Comedy&nbsp;→ Slapstick comedies", "Courtroom, Crime, Espionage & Thrillers", "Courtroom, Crime, Espionage & Thrillers&nbsp;→ Detective and mystery films", "Feature films", "Feature films&nbsp;→ Feature films - Great Britain", "Horror"]}, {"label": "Sound/audio", "display_values": ["Sound"]}, {"label": "Colour", "display_values": ["Colour"]}], "stats": {"tap_count": 0}, "links": [], "creators_primary": [{"id": 2245910, "name": "Gerald Thomas", "creator_id": 25067, "creator_wikidata_id": "Q740649", "role": "director", "role_id": 938, "is_primary": true}, {"id": 2245908, "name": "Peter Rogers", "creator_id": 25066, "creator_wikidata_id": "Q715904", "role": "producer", "role_id": 1089, "is_primary": true}, {"id": 2245906, "name": "Peter Rogers", "creator_id": 25066, "creator_wikidata_id": "Q715904", "role": "production company", "role_id": 941, "is_primary": true}], "creators_other": [], "media_note": "Sorry, we aren't able to make images or video for this item available to the public online.", "holdings": [{"name": "VHS; Access Print (Section 1)", "identifier": "", "description": ""}], "part_of": null, "parts": [], "part_siblings": [], "group": {"id": 115530, "acmi_id": "S01357", "title": "Carry on", "title_annotation": "", "slug": "carry-on", "creator_credit": "Gerald Thomas, Peter Rogers, Adder Productions and Rank Organisation Film Productions", "credit_line": "", "headline_credit": "United Kingdom", "video_links": [], "record_type": "group", "type": "Film", "is_on_display": false, "last_on_display_place": null, "last_on_display_date": null, "is_context_indigenous": false, "material_description": "", "unpublished": false, "external": false, "first_production_date": null, "commissioned": false, "public_domain": false, "external_references": [{"id": 53504, "source": {"name": "Wikidata", "slug": "wikidata"}, "source_identifier": "Q948916"}]}, "group_works": [], "group_siblings": [{"id": 89035, "acmi_id": "311661", "title": "Carry on abroad: or, what a package: or, it's all in: or, Swiss hols in the snow", "title_annotation": "", "slug": "carry-on-abroad-or-what-a-package-or-its-all-in-or-swiss-hols-in-the-snow", "creator_credit": "Gerald Thomas, Peter Rogers and Rank Organisation Film Productions", "credit_line": "", "headline_credit": "United Kingdom, 1972", "video_links": [], "record_type": "work", "type": "Film", "is_on_display": false, "last_on_display_place": null, "last_on_display_date": null, "is_context_indigenous": false, "material_description": "", "unpublished": false, "external": false, "first_production_date": "1972-01-01T11:00:00+11:00", "commissioned": false, "public_domain": false, "external_references": []}, {"id": 92984, "acmi_id": "316341", "title": "Carry on camping = Let sleeping bags lie", "title_annotation": "", "slug": "carry-on-camping-let-sleeping-bags-lie", "creator_credit": "Gerald Thomas, Peter Rogers, Adder Productions and Rank Organisation Film Productions", "credit_line": "", "headline_credit": "United Kingdom, 1969", "video_links": [], "record_type": "work", "type": "Film", "is_on_display": false, "last_on_display_place": null, "last_on_display_date": null, "is_context_indigenous": false, "material_description": "", "unpublished": false, "external": false, "first_production_date": "1969-01-01T10:00:00+10:00", "commissioned": false, "public_domain": false, "external_references": [{"id": 44309, "source": {"name": "Wikidata", "slug": "wikidata"}, "source_identifier": "Q449207"}]}, {"id": 92940, "acmi_id": "316282", "title": "Carry on constable", "title_annotation": "", "slug": "carry-on-constable", "creator_credit": "Gerald Thomas, Peter Rogers and Peter Rogers Productions", "credit_line": "", "headline_credit": "United Kingdom, 1961", "video_links": [], "record_type": "work", "type": "Film", "is_on_display": false, "last_on_display_place": null, "last_on_display_date": null, "is_context_indigenous": false, "material_description": "", "unpublished": false, "external": false, "first_production_date": "1961-01-01T10:00:00+10:00", "commissioned": false, "public_domain": false, "external_references": [{"id": 47991, "source": {"name": "Wikidata", "slug": "wikidata"}, "source_identifier": "Q1325568"}]}, {"id": 89037, "acmi_id": "311663", "title": "Carry on Dick", "title_annotation": "", "slug": "carry-on-dick", "creator_credit": "Gerald Thomas, Peter Rogers and Rank Organisation Film Productions", "credit_line": "", "headline_credit": "United Kingdom, 1974", "video_links": [], "record_type": "work", "type": "Film", "is_on_display": false, "last_on_display_place": null, "last_on_display_date": null, "is_context_indigenous": false, "material_description": "", "unpublished": false, "external": false, "first_production_date": "1974-01-01T11:00:00+11:00", "commissioned": false, "public_domain": false, "external_references": [{"id": 47126, "source": {"name": "Wikidata", "slug": "wikidata"}, "source_identifier": "Q302927"}]}, {"id": 89034, "acmi_id": "311660", "title": "Carry on doctor", "title_annotation": "", "slug": "carry-on-doctor", "creator_credit": "Gerald Thomas, Peter Rogers and Rank Organisation Film Productions", "credit_line": "", "headline_credit": "United Kingdom, 1967", "video_links": [], "record_type": "work", "type": "Film", "is_on_display": false, "last_on_display_place": null, "last_on_display_date": null, "is_context_indigenous": false, "material_description": "", "unpublished": false, "external": false, "first_production_date": "1967-01-01T10:00:00+10:00", "commissioned": false, "public_domain": false, "external_references": [{"id": 44774, "source": {"name": "Wikidata", "slug": "wikidata"}, "source_identifier": "Q179508"}]}, {"id": 82933, "acmi_id": "325383", "title": "Carry on doctor (Captioned)", "title_annotation": "", "slug": "carry-on-doctor-captioned", "creator_credit": "Gerald Thomas, Peter Rogers and Rank Organisation Film Productions", "credit_line": "", "headline_credit": "United Kingdom, 1967", "video_links": [], "record_type": "work", "type": "Film", "is_on_display": false, "last_on_display_place": null, "last_on_display_date": null, "is_context_indigenous": false, "material_description": "", "unpublished": false, "external": false, "first_production_date": "1967-01-01T10:00:00+10:00", "commissioned": false, "public_domain": false, "external_references": [{"id": 44245, "source": {"name": "Wikidata", "slug": "wikidata"}, "source_identifier": "Q179508"}]}, {"id": 92983, "acmi_id": "316340", "title": "Carry on Henry = Mind my chopper", "title_annotation": "", "slug": "carry-on-henry-mind-my-chopper", "creator_credit": "Gerald Thomas, Peter Rogers and Adder Productions", "credit_line": "", "headline_credit": "United Kingdom, 1970", "video_links": [], "record_type": "work", "type": "Film", "is_on_display": false, "last_on_display_place": null, "last_on_display_date": null, "is_context_indigenous": false, "material_description": "", "unpublished": false, "external": false, "first_production_date": "1970-01-01T10:00:00+10:00", "commissioned": false, "public_domain": false, "external_references": [{"id": 47111, "source": {"name": "Wikidata", "slug": "wikidata"}, "source_identifier": "Q449222"}]}, {"id": 92854, "acmi_id": "316191", "title": "Carry on sergeant", "title_annotation": "", "slug": "carry-on-sergeant", "creator_credit": "Gerald Thomas, Peter Rogers and Nat Cohen and Stuart Levy Productions", "credit_line": "", "headline_credit": "United Kingdom, 1958", "video_links": [], "record_type": "work", "type": "Film", "is_on_display": false, "last_on_display_place": null, "last_on_display_date": null, "is_context_indigenous": false, "material_description": "", "unpublished": false, "external": false, "first_production_date": "1958-01-01T10:00:00+10:00", "commissioned": false, "public_domain": false, "external_references": [{"id": 43729, "source": {"name": "Wikidata", "slug": "wikidata"}, "source_identifier": "Q1489818"}]}, {"id": 89036, "acmi_id": "311662", "title": "Carry on up the Khyber", "title_annotation": "", "slug": "carry-on-up-the-khyber", "creator_credit": "Gerald Thomas, Peter Rogers, Peter Rogers Productions and Rank Film Productions", "credit_line": "", "headline_credit": "United Kingdom, 1968", "video_links": [], "record_type": "work", "type": "Film", "is_on_display": false, "last_on_display_place": null, "last_on_display_date": null, "is_context_indigenous": false, "material_description": "", "unpublished": false, "external": false, "first_production_date": "1968-01-01T10:00:00+10:00", "commissioned": false, "public_domain": false, "external_references": [{"id": 46427, "source": {"name": "Wikidata", "slug": "wikidata"}, "source_identifier": "Q448090"}]}, {"id": 82934, "acmi_id": "325384", "title": "Carry on up the Khyber (Captioned)", "title_annotation": "", "slug": "carry-on-up-the-khyber-captioned", "creator_credit": "Gerald Thomas, Peter Rogers, Peter Rogers Productions and Rank Film Productions", "credit_line": "", "headline_credit": "United Kingdom, 1968", "video_links": [], "record_type": "work", "type": "Film", "is_on_display": false, "last_on_display_place": null, "last_on_display_date": null, "is_context_indigenous": false, "material_description": "", "unpublished": false, "external": false, "first_production_date": "1968-01-01T10:00:00+10:00", "commissioned": false, "public_domain": false, "external_references": [{"id": 46832, "source": {"name": "Wikidata", "slug": "wikidata"}, "source_identifier": "Q448090"}]}, {"id": 92985, "acmi_id": "316342", "title": "Don't lose your head", "title_annotation": "", "slug": "dont-lose-your-head", "creator_credit": "Gerald Thomas, Peter Rogers and Adder Productions", "credit_line": "", "headline_credit": "United Kingdom, 1966", "video_links": [], "record_type": "work", "type": "Film", "is_on_display": false, "last_on_display_place": null, "last_on_display_date": null, "is_context_indigenous": false, "material_description": "", "unpublished": false, "external": false, "first_production_date": "1966-01-01T10:00:00+10:00", "commissioned": false, "public_domain": false, "external_references": [{"id": 44758, "source": {"name": "Wikidata", "slug": "wikidata"}, "source_identifier": "Q1538005"}]}, {"id": 92986, "acmi_id": "316343", "title": "Follow that camel", "title_annotation": "", "slug": "follow-that-camel", "creator_credit": "Gerald Thomas, Peter Rogers and Peter Rogers Productions", "credit_line": "", "headline_credit": "United Kingdom, 1967", "video_links": [], "record_type": "work", "type": "Film", "is_on_display": false, "last_on_display_place": null, "last_on_display_date": null, "is_context_indigenous": false, "material_description": "", "unpublished": false, "external": false, "first_production_date": "1967-01-01T10:00:00+10:00", "commissioned": false, "public_domain": false, "external_references": [{"id": 46284, "source": {"name": "Wikidata", "slug": "wikidata"}, "source_identifier": "Q1674807"}]}], "source": {"name": "Vernon", "slug": "vernon"}, "source_identifier": "50366", "eaas_environment_id": null, "production_places": [{"id": 10, "name": "United Kingdom", "slug": "united-kingdom"}], "production_dates": [{"date": "1966", "notes": "Copyrighted", "to_year": "1966"}], "labels": [32343]}, {"id": 92852, "acmi_id": "316188", "title": "The Ruling class [DVD]", "title_annotation": "", "slug": "the-ruling-class-dvd", "creator_credit": "Peter Medak, Jack Hawkins, Jules Buck and Keep Films", "credit_line": "", "headline_credit": "United Kingdom, 1972", "video_links": [], "record_type": "work", "type": "Film", "is_on_display": false, "last_on_display_place": null, "last_on_display_date": null, "is_context_indigenous": false, "material_description": "", "unpublished": false, "external": false, "first_production_date": "1972-01-01T11:00:00+11:00", "commissioned": false, "public_domain": false, "external_references": [{"id": 47858, "source": {"name": "Wikidata", "slug": "wikidata"}, "source_identifier": "Q1890531"}], "brief_description": "<p>Based on the stage play by Peter Barnes, this screen adaptation of &#8220;The Ruling class&#8221; (also written by Peter Barnes) remains true to the original farcical and darkly comic tale of British aristocracy. Combining the use of melodrama, musical and horror film genres, Peter Medak has created a totally bizarre visual feast of irony and parody of upper class England revolving around the rather unusual death of a British lord (Harry Andrews) who accidently hangs himself while in military uniform and a ballerina&#8217;s tutu. The Earl&#8217;s son, Jack Gurney (Peter O&#8217;Toole) becomes the 14th Earl of Gurney and finds himself named in the will as heir to the Gurney Estate. Only one problem - Jack is a paranoid schizophrenic who believes he is Jesus Christ. Jack&#8217;s disinherited relatives resolve to maintain their pride and their position as an upper class family and plot to have Jack committed to a mental institution and leave them as guardians to the Gurney Estate. However, Jack has to produce a family heir before any of this can take place. The lengths the family go to and the unexpected, hilarious and truly bizarre outcomes of their efforts, including Jack beginning to secretly think that he is Jack the Ripper and murdering one of the family members, add up to a most unusual and enjoyable cinematic experience consisting of narrative and vaudeville song-and-dance sequences, mixed in with a good measure of black comedy and contempt for the British class system. Cast also includes Arthur Lowe, Alastair Sim, Coral Browne, Michael Bryant, William Mervyn, Carolyn Seymour.</p>", "constellations_primary": [], "constellations_other": [], "recommendations": [], "creator_credit_for_label": "<p>Peter Medak, Jack Hawkins, Jules Buck and Keep Films</p>", "headline_credit_for_label": "<p>United Kingdom, 1972</p>", "title_for_label": "<p>The Ruling class [DVD]</p>", "description": "<p>Based on the stage play by Peter Barnes, this screen adaptation of &#8220;The Ruling class&#8221; (also written by Peter Barnes) remains true to the original farcical and darkly comic tale of British aristocracy. Combining the use of melodrama, musical and horror film genres, Peter Medak has created a totally bizarre visual feast of irony and parody of upper class England revolving around the rather unusual death of a British lord (Harry Andrews) who accidently hangs himself while in military uniform and a ballerina&#8217;s tutu. The Earl&#8217;s son, Jack Gurney (Peter O&#8217;Toole) becomes the 14th Earl of Gurney and finds himself named in the will as heir to the Gurney Estate. Only one problem - Jack is a paranoid schizophrenic who believes he is Jesus Christ. Jack&#8217;s disinherited relatives resolve to maintain their pride and their position as an upper class family and plot to have Jack committed to a mental institution and leave them as guardians to the Gurney Estate. However, Jack has to produce a family heir before any of this can take place. The lengths the family go to and the unexpected, hilarious and truly bizarre outcomes of their efforts, including Jack beginning to secretly think that he is Jack the Ripper and murdering one of the family members, add up to a most unusual and enjoyable cinematic experience consisting of narrative and vaudeville song-and-dance sequences, mixed in with a good measure of black comedy and contempt for the British class system. Cast also includes Arthur Lowe, Alastair Sim, Coral Browne, Michael Bryant, William Mervyn, Carolyn Seymour.</p>", "description_for_label": ["<p>Based on the stage play by Peter Barnes, this screen adaptation of &#8220;The Ruling class&#8221; (also written by Peter Barnes) remains true to the original farcical and darkly comic tale of British aristocracy. Combining the use of melodrama, musical and horror film genres, Peter Medak has created a totally bizarre visual feast of irony and parody of upper class England revolving around the rather unusual death of a British lord (Harry Andrews) who accidently hangs himself while in military uniform and a ballerina&#8217;s tutu. The Earl&#8217;s son, Jack Gurney (Peter O&#8217;Toole) becomes the 14th Earl of Gurney and finds himself named in the will as heir to the Gurney Estate. Only one problem - Jack is a paranoid schizophrenic who believes he is Jesus Christ. Jack&#8217;s disinherited relatives resolve to maintain their pride and their position as an upper class family and plot to have Jack committed to a mental institution and leave them as guardians to the Gurney Estate. However, Jack has to produce a family heir before any of this can take place. The lengths the family go to and the unexpected, hilarious and truly bizarre outcomes of their efforts, including Jack beginning to secretly think that he is Jack the Ripper and murdering one of the family members, add up to a most unusual and enjoyable cinematic experience consisting of narrative and vaudeville song-and-dance sequences, mixed in with a good measure of black comedy and contempt for the British class system. Cast also includes Arthur Lowe, Alastair Sim, Coral Browne, Michael Bryant, William Mervyn, Carolyn Seymour.</p>"], "credit_line_for_label": "", "details": [{"label": "Duration", "display_values": ["02:34:00:00"]}, {"label": "Languages", "display_values": ["English", "English"]}, {"label": "Audience classification", "display_values": ["MA"]}, {"label": "Subject categories", "display_values": ["Comedy", "Comedy&nbsp;→ Black comedy", "Comedy&nbsp;→ Farce", "Comedy&nbsp;→ Parody", "Economics, Philosophy, Politics, Religion & Sociology&nbsp;→ Class consciousness", "Economics, Philosophy, Politics, Religion & Sociology&nbsp;→ Inheritance and succession", "Feature films", "Feature films&nbsp;→ Feature films - Great Britain", "Food, Health, Lifestyle, Medicine, Psychology & Safety&nbsp;→ Inheritance and succession", "Music & Performing Arts&nbsp;→ Vaudeville"]}, {"label": "Sound/audio", "display_values": ["Sound"]}, {"label": "Colour", "display_values": ["Colour"]}], "stats": {"tap_count": 0}, "links": [{"url": "https://www.justwatch.com/au/movie/the-ruling-class", "title": "Stream, rent or buy at <span>JustWatch</span>", "source": "justwatch"}], "creators_primary": [{"id": 1996769, "name": "Peter Medak", "creator_id": 25548, "creator_wikidata_id": "Q724100", "role": "director", "role_id": 938, "is_primary": true}, {"id": 1996768, "name": "Jack Hawkins", "creator_id": 80017, "creator_wikidata_id": "Q26118", "role": "co-producer", "role_id": 915, "is_primary": true}, {"id": 1996767, "name": "Jules Buck", "creator_id": 23715, "creator_wikidata_id": null, "role": "co-producer", "role_id": 915, "is_primary": true}, {"id": 1996766, "name": "Keep Films", "creator_id": 34548, "creator_wikidata_id": null, "role": "production company", "role_id": 941, "is_primary": true}], "creators_other": [], "media_note": "Sorry, we aren't able to make images or video for this item available to the public online.", "holdings": [{"name": "DVD; Access Print (Section 1)", "identifier": "", "description": ""}], "part_of": null, "parts": [], "part_siblings": [], "group": null, "group_works": [], "group_siblings": [], "source": {"name": "Vernon", "slug": "vernon"}, "source_identifier": "50364", "eaas_environment_id": null, "production_places": [{"id": 10, "name": "United Kingdom", "slug": "united-kingdom"}], "production_dates": [{"date": "1972", "notes": "Copyrighted", "to_year": "1972"}], "labels": [32342]}]}